README.md
pyproject.toml
setup.py
apigptcloud/__init__.py
apigptcloud.egg-info/PKG-INFO
apigptcloud.egg-info/SOURCES.txt
apigptcloud.egg-info/dependency_links.txt
apigptcloud.egg-info/requires.txt
apigptcloud.egg-info/top_level.txt
apigptcloud/aichat/ChatCompletion.py
apigptcloud/aichat/Embedding.py
apigptcloud/aichat/__init__.py
apigptcloud/chatglm/ChatCompletion.py
apigptcloud/chatglm/__init__.py
apigptcloud/claude/Completion.py
apigptcloud/claude/__init__.py
apigptcloud/openai/ChatCompletion.py
apigptcloud/openai/Completion.py
apigptcloud/openai/Embedding.py
apigptcloud/openai/__init__.py
apigptcloud/stablediffusion/__init__.py
apigptcloud/stablediffusion/draw.py